odoo/addons/partner_delivery_info/README.rst
odoo/addons/partner_delivery_info/__init__.py
odoo/addons/partner_delivery_info/__manifest__.py
odoo/addons/partner_delivery_info/i18n/es.po
odoo/addons/partner_delivery_info/i18n/it.po
odoo/addons/partner_delivery_info/i18n/partner_delivery_info.pot
odoo/addons/partner_delivery_info/models/__init__.py
odoo/addons/partner_delivery_info/models/res_partner.py
odoo/addons/partner_delivery_info/models/res_partner_delivery_info.py
odoo/addons/partner_delivery_info/readme/CONTRIBUTORS.md
odoo/addons/partner_delivery_info/readme/CREDITS.md
odoo/addons/partner_delivery_info/readme/DESCRIPTION.md
odoo/addons/partner_delivery_info/security/ir.model.access.csv
odoo/addons/partner_delivery_info/static/description/icon.png
odoo/addons/partner_delivery_info/static/description/index.html
odoo/addons/partner_delivery_info/views/menus.xml
odoo/addons/partner_delivery_info/views/res_partner.xml
odoo/addons/partner_delivery_info/views/res_partner_delivery_info.xml
odoo_addon_partner_delivery_info-18.0.1.0.0.5.dist-info/METADATA
odoo_addon_partner_delivery_info-18.0.1.0.0.5.dist-info/WHEEL
odoo_addon_partner_delivery_info-18.0.1.0.0.5.dist-info/top_level.txt
odoo_addon_partner_delivery_info-18.0.1.0.0.5.dist-info/RECORD
